pyAitu/__init__.py
pyAitu/bot/__init__.py
pyAitu/bot/api.py
pyAitu/bot/base.py
pyAitu/bot/bot.py
pyAitu/dispatcher/__init__.py
pyAitu/dispatcher/dispatcher.py
pyAitu/dispatcher/filters.py
pyAitu/dispatcher/handler.py
pyAitu/dispatcher/middlewares.py
pyAitu/dispatcher/storage.py
pyAitu/dispatcher/webhook.py
pyAitu/models/__init__.py
pyAitu/models/command/__init__.py
pyAitu/models/command/command.py
pyAitu/models/command/form_message.py
pyAitu/models/command/inline_command.py
pyAitu/models/command/quick_button_command.py
pyAitu/models/command/reply_command.py
pyAitu/models/command/uiState.py
pyAitu/models/constants/__init__.py
pyAitu/models/constants/alignment.py
pyAitu/models/constants/currency.py
pyAitu/models/constants/file_type.py
pyAitu/models/constants/input_type.py
pyAitu/models/constants/option_media_type.py
pyAitu/models/constants/orientation.py
pyAitu/models/constants/text_size.py
pyAitu/models/constants/text_style.py
pyAitu/models/form/__init__.py
pyAitu/models/form/bottom_bar.py
pyAitu/models/form/flex_options.py
pyAitu/models/form/form.py
pyAitu/models/form/form_action.py
pyAitu/models/form/header.py
pyAitu/models/form/indent.py
pyAitu/models/form/options.py
pyAitu/models/form/validation_rule.py
pyAitu/models/form/content/__init__.py
pyAitu/models/form/content/button.py
pyAitu/models/form/content/checkbox.py
pyAitu/models/form/content/content.py
pyAitu/models/form/content/custom_container.py
pyAitu/models/form/content/date_picker.py
pyAitu/models/form/content/divider.py
pyAitu/models/form/content/file_metadata.py
pyAitu/models/form/content/image.py
pyAitu/models/form/content/input.py
pyAitu/models/form/content/item.py
pyAitu/models/form/content/item_button.py
pyAitu/models/form/content/item_info.py
pyAitu/models/form/content/labeled_text.py
pyAitu/models/form/content/media_picker.py
pyAitu/models/form/content/radiogroup.py
pyAitu/models/form/content/simple_catalog.py
pyAitu/models/form/content/slider.py
pyAitu/models/form/content/submit.py
pyAitu-0.0.7.dist-info/LICENSE
pyAitu-0.0.7.dist-info/METADATA
pyAitu-0.0.7.dist-info/WHEEL
pyAitu-0.0.7.dist-info/top_level.txt
pyAitu-0.0.7.dist-info/RECORD
