Metadata-Version: 2.1
Name: pyAitu
Version: 0.0.7
Summary: Asynchronous Python framework for Aitu Bot API
Home-page: https://github.com/btsdigital/pyAitu
Author: Yerassyl Zeinolla
Author-email: yerassyl.zeinolla@btsdigital.kz
License: Apache 2.0
Platform: UNKNOWN
Classifier: Programming Language :: Python :: 3.7
Classifier: License :: OSI Approved :: Apache Software License
Requires-Python: >=3.7
Requires-Dist: aiohttp (<4.0.0,>=3.5.4)
Requires-Dist: certifi (>=2018.8.24)
